README.md
setup.py
megatools/__init__.py
megatools/megatools.py
megatools.egg-info/PKG-INFO
megatools.egg-info/SOURCES.txt
megatools.egg-info/dependency_links.txt
megatools.egg-info/top_level.txt