Metadata-Version: 2.1
Name: megatools
Version: 0.0.4
Summary: Megatools's wrapper
Home-page: https://github.com/Harkame/Megatools
Author: Harkame
License: UNKNOWN
Platform: UNKNOWN
Classifier: Programming Language :: Python
Classifier: License :: OSI Approved
Classifier: Operating System :: OS Independent
Requires-Python: >=3.6
